audit_log_client/__init__.py
audit_log_client/_version.py
audit_log_client/client.py
audit_log_client/models.py
audit_log_client/settings.py
audit_log_client/tools.py
audit_log_client-1.4.14.dist-info/licenses/LICENSE
audit_log_client-1.4.14.dist-info/METADATA
audit_log_client-1.4.14.dist-info/WHEEL
audit_log_client-1.4.14.dist-info/top_level.txt
audit_log_client-1.4.14.dist-info/RECORD
