Metadata-Version: 2.4
Name: audit-log-client
Version: 1.4.14
Summary: Python client for audit logging services
Author-email: Your Name <your.email@example.com>
License: MIT
Project-URL: homepage, https://github.com/yourusername/audit-log-client
Project-URL: Bug Tracker, https://github.com/yourusername/audit-log-client/issues
Project-URL: Documentation, https://github.com/yourusername/audit-log-client/wiki
Keywords: audit,logging,security,monitoring
Classifier: Programming Language :: Python :: 3
Classifier: License :: OSI Approved :: MIT License
Classifier: Operating System :: OS Independent
Requires-Python: >=3.7
License-File: LICENSE
Requires-Dist: httpx>=0.23.0
Requires-Dist: pydantic>=2.0.0
Provides-Extra: dev
Requires-Dist: pytest>=7.0; extra == "dev"
Requires-Dist: pytest-asyncio>=0.20.0; extra == "dev"
Requires-Dist: twine>=4.0.0; extra == "dev"
Requires-Dist: build>=0.10.0; extra == "dev"
Requires-Dist: bumpversion>=0.6.0; extra == "dev"
Dynamic: license-file
